<?xml version="1.0" encoding="utf-8" ?>
<dwsync>
<file name="6.php" server="104.219.248.42" local="131634407230696178" remote="131634406800000000" Dst="1" />
<file name="2.php" server="104.219.248.42" local="131634636403899138" remote="131634636000000000" Dst="1" />
<file name="3.php" server="104.219.248.42" local="131634636446371844" remote="131634636000000000" Dst="1" />
<file name="0.php" server="104.219.248.42" local="131634636246539180" remote="131634636000000000" Dst="1" />
<file name="1.php" server="104.219.248.42" local="131634636353095898" remote="131634636000000000" Dst="1" />
<file name="4.php" server="104.219.248.42" local="131634634549025882" remote="131634634200000000" Dst="1" />
<file name="5.php" server="104.219.248.42" local="131634634731502025" remote="131634634200000000" Dst="1" />
<file name="7.php" server="104.219.248.42" local="131634635127165318" remote="131634634800000000" Dst="1" />
</dwsync>